{
   "annotation": { "description": "US survey feet." },
   "typeid": "autodesk.unit.unit:usSurveyFeet-1.0.0",
   "inherits": [ "autodesk.unit:unit.derived-1.0.1" ],
   "constants": [
      { "id": "name", "value": "US survey feet" },
      { "id": "unitSystem", "value": "Imperial" },
      { "id": "factor", "value": 1200 },
      { "id": "parentFactors", "value": { "autodesk.unit.factor:threeThousandNineHundredThirtySeven-1.0.0": -1 } },
      { "id": "parentUnits", "value": { "autodesk.unit.unit:meters-1.0.0": 1 } }
   ]
}
